CHANGELOG.rst
LICENSE.txt
MANIFEST.in
README.rst
requirements.txt
setup.cfg
setup.py
docs/Makefile
docs/make.bat
docs/source/changelog.rst
docs/source/conf.py
docs/source/index.rst
docs/source/readme.rst
docs/source/api/api.rst
docs/source/api/engine.rst
docs/source/api/filters.rst
docs/source/api/gears.rst
docs/source/api/reaction_rules.rst
docs/source/api/steering_wheel.rst
docs/source/api/utilities.rst
docs/source/api/generated/scine_chemoton.filters.aggregate_filters.rst
docs/source/api/generated/scine_chemoton.filters.elementary_step_filters.rst
docs/source/api/generated/scine_chemoton.filters.further_exploration_filters.rst
docs/source/api/generated/scine_chemoton.filters.reaction_filters.rst
docs/source/api/generated/scine_chemoton.filters.reactive_site_filters.rst
docs/source/api/generated/scine_chemoton.filters.rst
docs/source/api/generated/scine_chemoton.filters.structure_filters.rst
docs/source/api/generated/scine_chemoton.gears.compound.rst
docs/source/api/generated/scine_chemoton.gears.conformers.brute_force.rst
docs/source/api/generated/scine_chemoton.gears.conformers.rst
docs/source/api/generated/scine_chemoton.gears.elementary_steps.brute_force.rst
docs/source/api/generated/scine_chemoton.gears.elementary_steps.minimal.rst
docs/source/api/generated/scine_chemoton.gears.elementary_steps.minimum_energy_conformer.rst
docs/source/api/generated/scine_chemoton.gears.elementary_steps.rst
docs/source/api/generated/scine_chemoton.gears.elementary_steps.selected_structures.rst
docs/source/api/generated/scine_chemoton.gears.elementary_steps.trial_generator.adsorptions.rst
docs/source/api/generated/scine_chemoton.gears.elementary_steps.trial_generator.bond_based.rst
docs/source/api/generated/scine_chemoton.gears.elementary_steps.trial_generator.connectivity_analyzer.rst
docs/source/api/generated/scine_chemoton.gears.elementary_steps.trial_generator.fast_dissociations.rst
scine_chemoton.egg-info/PKG-INFO
scine_chemoton.egg-info/SOURCES.txt
scine_chemoton.egg-info/dependency_links.txt
scine_chemoton.egg-info/entry_points.txt
scine_chemoton.egg-info/not-zip-safe
scine_chemoton.egg-info/requires.txt
scine_chemoton.egg-info/top_level.txt
