Metadata-Version: 2.1
Name: scine-chemoton
Version: 4.1.0
Summary: Software driving the automated exploration of chemical reaction networks
Home-page: https://www.scine.ethz.ch
Author: ETH Zurich, Department of Chemistry and Applied Biosciences, Reiher Group
Author-email: scine@phys.chem.ethz.ch
License: BSD (3-clause)
Classifier: Programming Language :: Python
Classifier: Programming Language :: C++
Classifier: Development Status :: 5 - Production/Stable
Classifier: Intended Audience :: Science/Research
Classifier: License :: OSI Approved :: BSD License
Classifier: Natural Language :: English
Classifier: Topic :: Scientific/Engineering :: Chemistry
Requires-Python: >=3.6
License-File: LICENSE.txt
